{
  "5b0d5b3b-ed7f-4dbb-a095-d4249d181dfb": {
    "gitAppName": "Test Custom Component",
    "lastCommitMessage": " v1 Version of app Test Custom Component promoted from development to staging",
    "gitVersionId": "3d29b060-4513-428a-87e0-b1f87e335b47",
    "lastpushDate": "2024-04-19T06:06:10.701Z",
    "gitVersionName": "v1",
    "lastCommitUser": "aman "
  },
  "acfa2ac6-11c8-4beb-a8fa-240874144b53": {
    "gitAppName": "AWS S3 file explorer",
    "lastCommitMessage": " v1 Version of app AWS S3 file explorer promoted from development to staging",
    "gitVersionId": "63b35f2a-d887-45b4-baf5-04811b7076aa",
    "lastpushDate": "2024-04-23T09:28:18.126Z",
    "gitVersionName": "v1",
    "lastCommitUser": "aman "
  },
  "85a2a465-4ad8-4e12-9615-859a78ab6eb4": {
    "gitAppName": "Supply-Chain-Management",
    "lastCommitMessage": " v1 Version of app Supply-Chain-Management promoted from development to staging",
    "gitVersionId": "798684d2-10f7-441a-8ac4-cb2a79c8ae31",
    "lastpushDate": "2024-05-02T11:47:28.338Z",
    "gitVersionName": "v1",
    "lastCommitUser": "aman "
  },
  "440094bf-de6b-44bc-8be5-e5694ab31b9e": {
    "gitAppName": "Student Enrolment Analysis",
    "lastCommitMessage": " v1 Version of app Student Enrolment Analysis promoted from development to staging",
    "gitVersionId": "9014a990-ec51-43d7-89a0-12b91c3e72ef",
    "lastpushDate": "2024-05-03T08:44:26.465Z",
    "gitVersionName": "v1",
    "lastCommitUser": "aman "
  }
}